heavymodel/__init__.py
heavymodel/basis.py
heavymodel/data.py
heavymodel/model.py
heavymodel/tables.py
heavymodel/yaml_validation.py
heavymodel_lewisfogden-0.0.2.dist-info/LICENSE
heavymodel_lewisfogden-0.0.2.dist-info/METADATA
heavymodel_lewisfogden-0.0.2.dist-info/WHEEL
heavymodel_lewisfogden-0.0.2.dist-info/top_level.txt
heavymodel_lewisfogden-0.0.2.dist-info/RECORD
