Metadata-Version: 2.1
Name: heavymodel-lewisfogden
Version: 0.0.2
Summary: Heavy Model Actuarial Modelling
Home-page: https://github.com/lewisfogden/heavymodel
Author: Lewis Fogden
Author-email: lewisfogden@gmail.com
License: UNKNOWN
Platform: UNKNOWN
Classifier: Programming Language :: Python :: 3
Classifier: License :: OSI Approved :: MIT License
Classifier: Operating System :: OS Independent
Requires-Python: >=3.6
